{
    "id": 123017,
    "dateTime": "2024-02-03T14:30:00Z",
    "lastCalculationDate": "2025-08-07T09:00:39.835725Z",
    "iterationId": 743,
    "squadHome": {
        "id": 34,
        "players": [
            {
                "id": 622,
                "shirtNumber": 28
            },
            {
                "id": 862,
                "shirtNumber": 22
            },
            {
                "id": 930,
                "shirtNumber": 26
            },
            {
                "id": 968,
                "shirtNumber": 38
            },
            {
                "id": 986,
                "shirtNumber": 17
            },
            {
                "id": 1050,
                "shirtNumber": 27
            },
            {
                "id": 1135,
                "shirtNumber": 5
            },
            {
                "id": 1268,
                "shirtNumber": 30
            },
            {
                "id": 1290,
                "shirtNumber": 21
            },
            {
                "id": 1294,
                "shirtNumber": 32
            },
            {
                "id": 1320,
                "shirtNumber": 8
            },
            {
                "id": 9604,
                "shirtNumber": 9
            },
            {
                "id": 23160,
                "shirtNumber": 23
            },
            {
                "id": 27747,
                "shirtNumber": 14
            },
            {
                "id": 29624,
                "shirtNumber": 6
            },
            {
                "id": 49785,
                "shirtNumber": 1
            },
            {
                "id": 62650,
                "shirtNumber": 25
            },
            {
                "id": 68933,
                "shirtNumber": 34
            },
            {
                "id": 94848,
                "shirtNumber": 33
            },
            {
                "id": 94862,
                "shirtNumber": 7
            }
        ],
        "startingPositions": [
            {
                "playerId": 622,
                "position": "CENTRAL_DEFENDER",
                "positionSide": "CENTRE_RIGHT"
            },
            {
                "playerId": 862,
                "position": "RIGHT_WINGER",
                "positionSide": "RIGHT"
            },
            {
                "playerId": 986,
                "position": "RIGHT_WINGBACK_DEFENDER",
                "positionSide": "RIGHT"
            },
            {
                "playerId": 1050,
                "position": "DEFENSE_MIDFIELD",
                "positionSide": "CENTRE_LEFT"
            },
            {
                "playerId": 1135,
                "position": "CENTRAL_DEFENDER",
                "positionSide": "CENTRE_LEFT"
            },
            {
                "playerId": 1294,
                "position": "LEFT_WINGER",
                "positionSide": "LEFT"
            },
            {
                "playerId": 1320,
                "position": "DEFENSE_MIDFIELD",
                "positionSide": "CENTRE_RIGHT"
            },
            {
                "playerId": 9604,
                "position": "CENTER_FORWARD",
                "positionSide": "CENTRE_LEFT"
            },
            {
                "playerId": 49785,
                "position": "GOALKEEPER",
                "positionSide": "CENTRE"
            },
            {
                "playerId": 68933,
                "position": "CENTER_FORWARD",
                "positionSide": "CENTRE_RIGHT"
            },
            {
                "playerId": 94848,
                "position": "LEFT_WINGBACK_DEFENDER",
                "positionSide": "LEFT"
            }
        ],
        "substitutions": [
            {
                "gameTime": {
                    "gameTime": "18:32.5290",
                    "gameTimeInSec": 1112.529
                },
                "playerId": 9604,
                "toPosition": "CENTER_FORWARD",
                "positionSide": "CENTRE",
                "fromPosition": "CENTER_FORWARD",
                "fromPositionSide": "CENTRE_LEFT",
                "exchangedPlayerId": null,
                "substitutionType": null
            },
            {
                "gameTime": {
                    "gameTime": "18:32.5290",
                    "gameTimeInSec": 1112.529
                },
                "playerId": 68933,
                "toPosition": "BANK",
                "positionSide": "UNKNOWN",
                "fromPosition": "CENTER_FORWARD",
                "fromPositionSide": "CENTRE_RIGHT",
                "exchangedPlayerId": null,
                "substitutionType": null
            },
            {
                "gameTime": {
                    "gameTime": "72:13.9670",
                    "gameTimeInSec": 11633.967
                },
                "playerId": 968,
                "toPosition": "CENTER_FORWARD",
                "positionSide": "CENTRE",
                "fromPosition": "BANK",
                "fromPositionSide": "UNKNOWN",
                "exchangedPlayerId": null,
                "substitutionType": null
            },
            {
                "gameTime": {
                    "gameTime": "72:13.9670",
                    "gameTimeInSec": 11633.967
                },
                "playerId": 1050,
                "toPosition": "BANK",
                "positionSide": "UNKNOWN",
                "fromPosition": "DEFENSE_MIDFIELD",
                "fromPositionSide": "CENTRE_LEFT",
                "exchangedPlayerId": null,
                "substitutionType": null
            },
            {
                "gameTime": {
                    "gameTime": "72:13.9670",
                    "gameTimeInSec": 11633.967
                },
                "playerId": 1268,
                "toPosition": "LEFT_WINGBACK_DEFENDER",
                "positionSide": "LEFT",
                "fromPosition": "BANK",
                "fromPositionSide": "UNKNOWN",
                "exchangedPlayerId": null,
                "substitutionType": null
            },
            {
                "gameTime": {
                    "gameTime": "72:13.9670",
                    "gameTimeInSec": 11633.967
                },
                "playerId": 1320,
                "toPosition": "DEFENSE_MIDFIELD",
                "positionSide": "CENTRE_LEFT",
                "fromPosition": "DEFENSE_MIDFIELD",
                "fromPositionSide": "CENTRE_RIGHT",
                "exchangedPlayerId": null,
                "substitutionType": null
            },
            {
                "gameTime": {
                    "gameTime": "72:13.9670",
                    "gameTimeInSec": 11633.967
                },
                "playerId": 9604,
                "toPosition": "DEFENSE_MIDFIELD",
                "positionSide": "CENTRE_RIGHT",
                "fromPosition": "CENTER_FORWARD",
                "fromPositionSide": "CENTRE",
                "exchangedPlayerId": null,
                "substitutionType": null
            },
            {
                "gameTime": {
                    "gameTime": "72:13.9670",
                    "gameTimeInSec": 11633.967
                },
                "playerId": 94848,
                "toPosition": "BANK",
                "positionSide": "UNKNOWN",
                "fromPosition": "LEFT_WINGBACK_DEFENDER",
                "fromPositionSide": "LEFT",
                "exchangedPlayerId": null,
                "substitutionType": null
            },
            {
                "gameTime": {
                    "gameTime": "82:25.2650",
                    "gameTimeInSec": 12245.265
                },
                "playerId": 622,
                "toPosition": "BANK",
                "positionSide": "UNKNOWN",
                "fromPosition": "CENTRAL_DEFENDER",
                "fromPositionSide": "CENTRE_RIGHT",
                "exchangedPlayerId": null,
                "substitutionType": null
            },
            {
                "gameTime": {
                    "gameTime": "82:25.2650",
                    "gameTimeInSec": 12245.265
                },
                "playerId": 930,
                "toPosition": "DEFENSE_MIDFIELD",
                "positionSide": "CENTRE_RIGHT",
                "fromPosition": "BANK",
                "fromPositionSide": "UNKNOWN",
                "exchangedPlayerId": null,
                "substitutionType": null
            },
            {
                "gameTime": {
                    "gameTime": "82:25.2650",
                    "gameTimeInSec": 12245.265
                },
                "playerId": 1135,
                "toPosition": "CENTRAL_DEFENDER",
                "positionSide": "CENTRE_RIGHT",
                "fromPosition": "CENTRAL_DEFENDER",
                "fromPositionSide": "CENTRE_LEFT",
                "exchangedPlayerId": null,
                "substitutionType": null
            },
            {
                "gameTime": {
                    "gameTime": "82:25.2650",
                    "gameTimeInSec": 12245.265
                },
                "playerId": 1294,
                "toPosition": "BANK",
                "positionSide": "UNKNOWN",
                "fromPosition": "LEFT_WINGER",
                "fromPositionSide": "LEFT",
                "exchangedPlayerId": null,
                "substitutionType": null
            },
            {
                "gameTime": {
                    "gameTime": "82:25.2650",
                    "gameTimeInSec": 12245.265
                },
                "playerId": 9604,
                "toPosition": "BANK",
                "positionSide": "UNKNOWN",
                "fromPosition": "DEFENSE_MIDFIELD",
                "fromPositionSide": "CENTRE_RIGHT",
                "exchangedPlayerId": null,
                "substitutionType": null
            },
            {
                "gameTime": {
                    "gameTime": "82:25.2650",
                    "gameTimeInSec": 12245.265
                },
                "playerId": 23160,
                "toPosition": "LEFT_WINGER",
                "positionSide": "LEFT",
                "fromPosition": "BANK",
                "fromPositionSide": "UNKNOWN",
                "exchangedPlayerId": null,
                "substitutionType": null
            },
            {
                "gameTime": {
                    "gameTime": "82:25.2650",
                    "gameTimeInSec": 12245.265
                },
                "playerId": 94862,
                "toPosition": "CENTRAL_DEFENDER",
                "positionSide": "CENTRE_LEFT",
                "fromPosition": "BANK",
                "fromPositionSide": "UNKNOWN",
                "exchangedPlayerId": null,
                "substitutionType": null
            }
        ],
        "startingFormation": "4-4-2 (flat)",
        "formations": [
            {
                "gameTime": "00:00.0000",
                "gameTimeInSec": 0.0,
                "formation": "4-4-2 (flat)"
            },
            {
                "gameTime": "18:32.5290",
                "gameTimeInSec": 1112.529,
                "formation": "UNKNOWN"
            }
        ],
        "coachId": null
    },
    "squadAway": {
        "id": 46,
        "players": [
            {
                "id": 1023,
                "shirtNumber": 33
            },
            {
                "id": 1161,
                "shirtNumber": 5
            },
            {
                "id": 1171,
                "shirtNumber": 15
            },
            {
                "id": 1297,
                "shirtNumber": 7
            },
            {
                "id": 1359,
                "shirtNumber": 2
            },
            {
                "id": 9861,
                "shirtNumber": 1
            },
            {
                "id": 22947,
                "shirtNumber": 16
            },
            {
                "id": 27123,
                "shirtNumber": 6
            },
            {
                "id": 27426,
                "shirtNumber": 4
            },
            {
                "id": 31448,
                "shirtNumber": 20
            },
            {
                "id": 33056,
                "shirtNumber": 32
            },
            {
                "id": 35172,
                "shirtNumber": 27
            },
            {
                "id": 44929,
                "shirtNumber": 26
            },
            {
                "id": 46337,
                "shirtNumber": 8
            },
            {
                "id": 51629,
                "shirtNumber": 18
            },
            {
                "id": 53526,
                "shirtNumber": 29
            },
            {
                "id": 104927,
                "shirtNumber": 46
            },
            {
                "id": 114859,
                "shirtNumber": 19
            },
            {
                "id": 162410,
                "shirtNumber": 45
            },
            {
                "id": 165748,
                "shirtNumber": 49
            }
        ],
        "startingPositions": [
            {
                "playerId": 1023,
                "position": "GOALKEEPER",
                "positionSide": "CENTRE"
            },
            {
                "playerId": 1297,
                "position": "LEFT_WINGBACK_DEFENDER",
                "positionSide": "LEFT"
            },
            {
                "playerId": 1359,
                "position": "CENTRAL_DEFENDER",
                "positionSide": "CENTRE"
            },
            {
                "playerId": 22947,
                "position": "DEFENSE_MIDFIELD",
                "positionSide": "CENTRE_RIGHT"
            },
            {
                "playerId": 27123,
                "position": "DEFENSE_MIDFIELD",
                "positionSide": "CENTRE_LEFT"
            },
            {
                "playerId": 27426,
                "position": "RIGHT_WINGBACK_DEFENDER",
                "positionSide": "RIGHT"
            },
            {
                "playerId": 31448,
                "position": "CENTRAL_DEFENDER",
                "positionSide": "CENTRE_RIGHT"
            },
            {
                "playerId": 35172,
                "position": "ATTACKING_MIDFIELD",
                "positionSide": "CENTRE_LEFT"
            },
            {
                "playerId": 44929,
                "position": "CENTER_FORWARD",
                "positionSide": "CENTRE"
            },
            {
                "playerId": 46337,
                "position": "ATTACKING_MIDFIELD",
                "positionSide": "CENTRE_RIGHT"
            },
            {
                "playerId": 53526,
                "position": "CENTRAL_DEFENDER",
                "positionSide": "CENTRE_LEFT"
            }
        ],
        "substitutions": [
            {
                "gameTime": {
                    "gameTime": "75:01.5780",
                    "gameTimeInSec": 11801.578
                },
                "playerId": 1161,
                "toPosition": "ATTACKING_MIDFIELD",
                "positionSide": "CENTRE_RIGHT",
                "fromPosition": "BANK",
                "fromPositionSide": "UNKNOWN",
                "exchangedPlayerId": null,
                "substitutionType": null
            },
            {
                "gameTime": {
                    "gameTime": "75:01.5780",
                    "gameTimeInSec": 11801.578
                },
                "playerId": 35172,
                "toPosition": "BANK",
                "positionSide": "UNKNOWN",
                "fromPosition": "ATTACKING_MIDFIELD",
                "fromPositionSide": "CENTRE_LEFT",
                "exchangedPlayerId": null,
                "substitutionType": null
            },
            {
                "gameTime": {
                    "gameTime": "75:01.5780",
                    "gameTimeInSec": 11801.578
                },
                "playerId": 46337,
                "toPosition": "BANK",
                "positionSide": "UNKNOWN",
                "fromPosition": "ATTACKING_MIDFIELD",
                "fromPositionSide": "CENTRE_RIGHT",
                "exchangedPlayerId": null,
                "substitutionType": null
            },
            {
                "gameTime": {
                    "gameTime": "75:01.5780",
                    "gameTimeInSec": 11801.578
                },
                "playerId": 51629,
                "toPosition": "ATTACKING_MIDFIELD",
                "positionSide": "CENTRE_LEFT",
                "fromPosition": "BANK",
                "fromPositionSide": "UNKNOWN",
                "exchangedPlayerId": null,
                "substitutionType": null
            },
            {
                "gameTime": {
                    "gameTime": "82:25.2650",
                    "gameTimeInSec": 12245.265
                },
                "playerId": 1171,
                "toPosition": "LEFT_WINGBACK_DEFENDER",
                "positionSide": "LEFT",
                "fromPosition": "BANK",
                "fromPositionSide": "UNKNOWN",
                "exchangedPlayerId": null,
                "substitutionType": null
            },
            {
                "gameTime": {
                    "gameTime": "82:25.2650",
                    "gameTimeInSec": 12245.265
                },
                "playerId": 1297,
                "toPosition": "BANK",
                "positionSide": "UNKNOWN",
                "fromPosition": "LEFT_WINGBACK_DEFENDER",
                "fromPositionSide": "LEFT",
                "exchangedPlayerId": null,
                "substitutionType": null
            }
        ],
        "startingFormation": "5-2-2-1",
        "formations": [
            {
                "gameTime": "00:00.0000",
                "gameTimeInSec": 0.0,
                "formation": "5-2-2-1"
            }
        ],
        "coachId": null
    }
}